junifer/__init__.py
junifer/__init__.pyi
junifer/_version.py
junifer/conftest.py
junifer/py.typed
junifer/stats.py
junifer/api/__init__.py
junifer/api/__init__.pyi
junifer/api/decorators.py
junifer/api/functions.py
junifer/api/py.typed
junifer/api/queue_context/__init__.py
junifer/api/queue_context/__init__.pyi
junifer/api/queue_context/gnu_parallel_local_adapter.py
junifer/api/queue_context/htcondor_adapter.py
junifer/api/queue_context/py.typed
junifer/api/queue_context/queue_context_adapter.py
junifer/api/queue_context/tests/test_gnu_parallel_local_adapter.py
junifer/api/queue_context/tests/test_htcondor_adapter.py
junifer/api/res/run_conda.bash
junifer/api/res/run_conda.zsh
junifer/api/res/run_venv.bash
junifer/api/res/run_venv.zsh
junifer/api/res/afni/3dAFNItoNIFTI
junifer/api/res/afni/3dRSFC
junifer/api/res/afni/3dReHo
junifer/api/res/afni/afni
junifer/api/res/afni/run_afni_docker.sh
junifer/api/res/ants/ResampleImage
junifer/api/res/ants/antsApplyTransforms
junifer/api/res/ants/antsApplyTransformsToPoints
junifer/api/res/ants/run_ants_docker.sh
junifer/api/res/freesurfer/mri_binarize
junifer/api/res/freesurfer/mri_mc
junifer/api/res/freesurfer/mri_pretess
junifer/api/res/freesurfer/mris_convert
junifer/api/res/freesurfer/run_freesurfer_docker.sh
junifer/api/res/fsl/applywarp
junifer/api/res/fsl/flirt
junifer/api/res/fsl/img2imgcoord
junifer/api/res/fsl/run_fsl_docker.sh
junifer/api/res/fsl/std2imgcoord
junifer/api/tests/test_functions.py
junifer/cli/__init__.py
junifer/cli/__init__.pyi
junifer/cli/cli.py
junifer/cli/parser.py
junifer/cli/py.typed
junifer/cli/utils.py
junifer/cli/tests/test_cli.py
junifer/cli/tests/test_cli_utils.py
junifer/cli/tests/test_parser.py
junifer/cli/tests/data/gmd_mean.yaml
junifer/cli/tests/data/gmd_mean_htcondor.yaml
junifer/cli/tests/data/partly_cloudy_agg_mean_tian.yml
junifer/configs/__init__.py
junifer/configs/juseless/__init__.py
junifer/configs/juseless/__init__.pyi
junifer/configs/juseless/py.typed
junifer-0.0.6.dist-info/licenses/AUTHORS.rst
junifer-0.0.6.dist-info/licenses/LICENSE.md
junifer-0.0.6.dist-info/METADATA
junifer-0.0.6.dist-info/WHEEL
junifer-0.0.6.dist-info/entry_points.txt
junifer-0.0.6.dist-info/top_level.txt
junifer-0.0.6.dist-info/RECORD
