Metadata-Version: 2.4
Name: junifer
Version: 0.0.6
Summary: JUelich NeuroImaging FEature extractoR
Author-email: Fede Raimondo <f.raimondo@fz-juelich.de>, Synchon Mandal <s.mandal@fz-juelich.de>
Maintainer-email: Fede Raimondo <f.raimondo@fz-juelich.de>, Synchon Mandal <s.mandal@fz-juelich.de>
License: AGPL-3.0-only
Project-URL: Changelog, https://juaml.github.io/junifer/main/whats_new.html
Project-URL: Documentation, https://juaml.github.io/junifer
Project-URL: Homepage, https://juaml.github.io/junifer
Project-URL: Source, https://github.com/juaml/junifer
Keywords: neuroimaging
Classifier: Development Status :: 4 - Beta
Classifier: Intended Audience :: Science/Research
Classifier: Intended Audience :: Developers
Classifier: License :: OSI Approved
Classifier: Natural Language :: English
Classifier: Topic :: Software Development
Classifier: Topic :: Scientific/Engineering
Classifier: Topic :: Scientific/Engineering :: Bio-Informatics
Classifier: Operating System :: OS Independent
Classifier: Programming Language :: Python :: 3.9
Classifier: Programming Language :: Python :: 3.10
Classifier: Programming Language :: Python :: 3.11
Classifier: Programming Language :: Python :: 3.12
Classifier: Programming Language :: Python :: 3.13
Requires-Python: >=3.9
License-File: LICENSE.md
License-File: AUTHORS.rst
Requires-Dist: click<8.2,>=8.1.3
Requires-Dist: numpy<2.0.0,>=1.26.0
Requires-Dist: scipy<=1.15.0,>=1.10.0
Requires-Dist: datalad<1.2.0,>=1.0.0
Requires-Dist: pandas<2.3.0,>=2.0.0
Requires-Dist: nibabel<5.4.0,>=5.2.0
Requires-Dist: nilearn<=0.10.4,>=0.10.3
Requires-Dist: sqlalchemy<=2.1.0,>=2.0.25
Requires-Dist: ruamel.yaml<0.19,>=0.17
Requires-Dist: h5py>=3.10
Requires-Dist: tqdm<4.67.0,>=4.66.1
Requires-Dist: templateflow>=23.0.0
Requires-Dist: lapy<2.0.0,>=1.0.0
Requires-Dist: lazy_loader==0.4
Requires-Dist: importlib_metadata; python_version < "3.9"
Requires-Dist: looseversion==1.3.0; python_version >= "3.12"
Requires-Dist: junifer_data==1.3.0
Provides-Extra: all
Requires-Dist: bctpy==0.6.0; extra == "all"
Requires-Dist: neurokit2>=0.1.7; extra == "all"
Provides-Extra: bct
Requires-Dist: bctpy==0.6.0; extra == "bct"
Provides-Extra: onthefly
Requires-Dist: bctpy==0.6.0; extra == "onthefly"
Provides-Extra: neurokit2
Requires-Dist: neurokit2>=0.1.7; extra == "neurokit2"
Provides-Extra: dev
Requires-Dist: tox; extra == "dev"
Requires-Dist: pre-commit; extra == "dev"
Provides-Extra: docs
Requires-Dist: seaborn<0.14.0,>=0.13.0; extra == "docs"
Requires-Dist: sphinx<8.1.0,>=7.3.0; extra == "docs"
Requires-Dist: sphinx-gallery<0.18.0,>=0.17.0; extra == "docs"
Requires-Dist: furo<2024.9.0,>=2024.4.27; extra == "docs"
Requires-Dist: numpydoc<1.9.0,>=1.6.0; extra == "docs"
Requires-Dist: julearn==0.3.3; extra == "docs"
Requires-Dist: sphinx-copybutton<0.5.3,>=0.5.1; extra == "docs"
Requires-Dist: towncrier<24.7.0,>=23.10.0; extra == "docs"
Requires-Dist: sphinxcontrib-mermaid<0.10,>=0.8.1; extra == "docs"
Requires-Dist: sphinxcontrib-towncrier==0.4.0a0; extra == "docs"
Requires-Dist: setuptools-scm>=8; extra == "docs"
Dynamic: license-file
